xt_neighbor_cpu/__init__.py
xt_neighbor_cpu/__main__.py
xt_neighbor_cpu/xt_neighbor.py
xt_neighbor_cpu-0.0.7.dist-info/METADATA
xt_neighbor_cpu-0.0.7.dist-info/WHEEL
xt_neighbor_cpu-0.0.7.dist-info/licenses/LICENSE
xt_neighbor_cpu-0.0.7.dist-info/RECORD
