Metadata-Version: 2.3
Name: xt_neighbor_cpu
Version: 0.0.7
Summary: A small example package
Project-URL: Homepage, https://github.com/heartnetkung/XT-neighbor-cpu
Project-URL: Issues, https://github.com/heartnetkung/XT-neighbor-cpu/issues
Author-email: heartnetkung <heartnetkung@gmail.com>
License-File: LICENSE
Classifier: License :: OSI Approved :: MIT License
Classifier: Operating System :: OS Independent
Classifier: Programming Language :: Python :: 3
Requires-Python: >=3.8
Requires-Dist: pyrepseq==1.5
